[
  {
    "text": "병원 곳곳에 무인종합안내기를 갖춰 편하게 병원 안내와 처방전, 각종 증명서를 발급받을 수 있도록 했다.",
    "answer": "갖추/VV+어/EC",
    "split_answer": [
      [
        "갖추",
        "VV"
      ],
      [
        "어",
        "EC"
      ]
    ]
  },
  {
    "text": "근린 생활 시설, 공영 주차장 등도 갖춰 복합 교육 문화 공간으로 조성했다.",
    "answer": "갖추/VV+어/EC",
    "split_answer": [
      [
        "갖추",
        "VV"
      ],
      [
        "어",
        "EC"
      ]
    ]
  },
  {
    "text": "김억의 우려에도 불구하고 1920년대 한국 시는 현대시로서의 면모를 갖춰 나갔다.",
    "answer": "갖추/VV+어/EC",
    "split_answer": [
      [
        "갖추",
        "VV"
      ],
      [
        "어",
        "EC"
      ]
    ]
  },
  {
    "text": "박성백 경쟁자는… 獨 슈타우프-뮐러 세계 정상급 실력 갖춰",
    "answer": "갖추/VV+어/EF",
    "split_answer": [
      [
        "갖추",
        "VV"
      ],
      [
        "어",
        "EF"
      ]
    ]
  },
  {
    "text": "서비스 품질 향상을 위해 기술적 전문성과 경영 마인드 갖춰",
    "answer": "갖추/VV+어/EF",
    "split_answer": [
      [
        "갖추",
        "VV"
      ],
      [
        "어",
        "EF"
      ]
    ]
  }
]