[
  {
    "text": "그러면 그렇게 따지만 이 용어도 사실 한 차례 더 수정이 가해져야 맞는 거긴 하네요.",
    "answer": "거/NNB+이/VCP+기/ETN+ㄴ/JX",
    "split_answer": [
      [
        "거",
        "NNB"
      ],
      [
        "이",
        "VCP"
      ],
      [
        "기",
        "ETN"
      ],
      [
        "ㄴ",
        "JX"
      ]
    ]
  },
  {
    "text": "이제 이 단계면은 높은 거긴 하지.",
    "answer": "거/NNB+이/VCP+기/ETN+ㄴ/JX",
    "split_answer": [
      [
        "거",
        "NNB"
      ],
      [
        "이",
        "VCP"
      ],
      [
        "기",
        "ETN"
      ],
      [
        "ㄴ",
        "JX"
      ]
    ]
  }
]