[
  {
    "text": "여름휴가 때마다 수중 촬영을 위해 디카용 비닐팩을 사용해보고, 일회용 수중카메라를 써본 것에 비교하자면, 탁월하다.",
    "answer": "것/NNB+에/JKB",
    "split_answer": [
      [
        "것",
        "NNB"
      ],
      [
        "에",
        "JKB"
      ]
    ]
  },
  {
    "text": "그리고 보수와 진보의 차이 중간 회색지대라고 하는 것에",
    "answer": "것/NNB+에/JKG",
    "split_answer": [
      [
        "것",
        "NNB"
      ],
      [
        "에",
        "JKG"
      ]
    ]
  },
  {
    "text": "또 궐석 재판 받더라도 것에 대한",
    "answer": "것/NP+에/JKB",
    "split_answer": [
      [
        "것",
        "NP"
      ],
      [
        "에",
        "JKB"
      ]
    ]
  },
  {
    "text": "어떤 것이든지 돼요. 어떤 것에 제 어떤 것드 것이든지 다 되는데.",
    "answer": "것에/NA",
    "split_answer": [
      "것에",
      "NA"
    ]
  }
]