[
  {
    "text": "간단히 답할 수 있는 것일지 모르겠지만, 분명히 복지정치와 조세정치 등 다각적인 측면에서 실증적으로 접근해 분석할 필요가 있어 보인다.",
    "answer": "것/NNB+이/VCP+ㄹ지/EC",
    "split_answer": [
      [
        "것",
        "NNB"
      ],
      [
        "이",
        "VCP"
      ],
      [
        "ㄹ지",
        "EC"
      ]
    ]
  },
  {
    "text": "연준의 기준금리 정책에 미묘한 변화를 시사하는 것일지 모른다는 관측이 나오고 있다고 전했다.",
    "answer": "것/NNB+이/VCP+ㄹ지/EF",
    "split_answer": [
      [
        "것",
        "NNB"
      ],
      [
        "이",
        "VCP"
      ],
      [
        "ㄹ지",
        "EF"
      ]
    ]
  }
]