[
  {
    "text": "이 경우 재상고를 하더라도 크게 실익이 없기 때문에 파기환송 사건은 '4심'으로 마무리되는 경우가 많다.",
    "answer": "경우/NNG+가/JKS",
    "split_answer": [
      [
        "경우",
        "NNG"
      ],
      [
        "가",
        "JKS"
      ]
    ]
  },
  {
    "text": "통신사들은 “금융 거래 실적이 부족한 사회 초년생이나 주부 등은 축적된 신용평가 자료가 없다는 이유로 신용등급이 낮게 평가되는 경우가 많은데, 통신 이용 정보 빅데이터 자료가 도움이 될 수 있다”고 설명했다.",
    "answer": "경우/NNG+가/JKS",
    "split_answer": [
      [
        "경우",
        "NNG"
      ],
      [
        "가",
        "JKS"
      ]
    ]
  },
  {
    "text": "하지만 이른바 산후풍으로 알려진 주요 증상들이 갑상선 기능의 문제로 생긴 '산후 갑상선염'인 경우가 많다고 전문의들은 말한다.",
    "answer": "경우/NNG+가/JKS",
    "split_answer": [
      [
        "경우",
        "NNG"
      ],
      [
        "가",
        "JKS"
      ]
    ]
  },
  {
    "text": "그러면서 헌재는 헌법재판소법 제53조 제1항 ‘탄핵심판청구가 이유 있는 때’란 “모든 법 위반의 경우가 아닌 공직자의 파면을 정당화할 정도로 중대한 법 위반의 경우를 의미한다”고 해석했다.",
    "answer": "경우/NNG+가/JKC",
    "split_answer": [
      [
        "경우",
        "NNG"
      ],
      [
        "가",
        "JKC"
      ]
    ]
  },
  {
    "text": "그래서 아주 극단적인 경우가 아니라면은요",
    "answer": "경우/NNG+가/JKC",
    "split_answer": [
      [
        "경우",
        "NNG"
      ],
      [
        "가",
        "JKC"
      ]
    ]
  },
  {
    "text": "나는 사실관계나 논리 전개가 분명치 않거나 반드시 들어갈 내용이 빠진 경우가 아니면 남이 쓴 기사는 되도록 손대지 않으려고 한다.",
    "answer": "경우/NNG+가/JKC",
    "split_answer": [
      [
        "경우",
        "NNG"
      ],
      [
        "가",
        "JKC"
      ]
    ]
  }
]