[
  {
    "text": "노세 우시조는 1926년 구스타프 아돌프 스웨덴 황태자를 수행해 경주 유적을 방문한 이래 31년까지 조선에서 신라, 고려 왕릉과 경주 황복사탑, 원원사탑, 구례 화엄사 석탑, 고대 십이지상 등을 조사했다.",
    "answer": "고대/NNG",
    "split_answer": [
      "고대",
      "NNG"
    ]
  },
  {
    "text": "고대 그리스 동전 10만개 등 총 54만개의 동전을 갖고 있다.",
    "answer": "고대/NNG",
    "split_answer": [
      "고대",
      "NNG"
    ]
  },
  {
    "text": "‘사막의 베네치아’라고 불리는 팔미라에는 1~2세기에 조성된 거대한 돌기둥들을 비롯한 고대 유적지들이 유네스코 세계유산으로 등재돼 있다.",
    "answer": "고대/NNG",
    "split_answer": [
      "고대",
      "NNG"
    ]
  },
  {
    "text": "연대 애들은 구두 닦고 고대 애들은 막걸리 마신다.",
    "answer": "고대/NNP",
    "split_answer": [
      "고대",
      "NNP"
    ]
  },
  {
    "text": "이번에 그 고대 가가지고",
    "answer": "고대/NNP",
    "split_answer": [
      "고대",
      "NNP"
    ]
  },
  {
    "text": "사람들한테 제가 고대 나왔다는 걸 더 자주 얘기하게 되는 거예요 명명백백하게.",
    "answer": "고대/NNP",
    "split_answer": [
      "고대",
      "NNP"
    ]
  }
]