[
  {
    "text": "현대건설에는 케니라는 걸출한 공격수가 있다.",
    "answer": "공격수/NNG+가/JKS",
    "split_answer": [
      [
        "공격수",
        "NNG"
      ],
      [
        "가",
        "JKS"
      ]
    ]
  },
  {
    "text": "수원은 공격수가 중원까지 내려와 수비진과 함께 서울 미드필더를 압박해 공격수에게 볼이 연결되지 못하게 했다”고 분석했다.",
    "answer": "공격수/NNG+가/JKS",
    "split_answer": [
      [
        "공격수",
        "NNG"
      ],
      [
        "가",
        "JKS"
      ]
    ]
  },
  {
    "text": "그는 공격수가 아닌 날개 자리로 경기에 나서거나 아예 출전하지 못했다.",
    "answer": "공격수/NNG+가/JKC",
    "split_answer": [
      [
        "공격수",
        "NNG"
      ],
      [
        "가",
        "JKC"
      ]
    ]
  }
]