[
  {
    "text": "다른 지역과 달리 독특한 길을 걸었던 그리스에서는 기원전 6세기 태동한 합리주의와 기원전 5세기에 번영한 비극이 자기 탐구와 공감의 발견을 통해 축의 시대를 이끌었다.",
    "answer": "공감/NNG+의/JKG",
    "split_answer": [
      [
        "공감",
        "NNG"
      ],
      [
        "의",
        "JKG"
      ]
    ]
  },
  {
    "text": "치열했지만 또 한편으로는 막연했던 연극의 열정과 패기는 이제 삶의 체험과 공감의 영역으로 조금씩 자리를 옮겨가고 있었다.",
    "answer": "공감/NNG+의/JKG",
    "split_answer": [
      [
        "공감",
        "NNG"
      ],
      [
        "의",
        "JKG"
      ]
    ]
  },
  {
    "text": "공익변호사그룹 공감의 황필규 변호사는 \"지난해 출입국 관리법 개정 이후 심사가 1년 이상 길어지면 일을 하도록 열어놓기는 했지만 실제 취업은 불가능하다\"며 \"현행 제도는 난민 신청자가 법을 지키고 굶어 죽을 것인지, 법을 어기고 살 것인지를 선택하도록 하고 있다\"고 비판했다.",
    "answer": "공감/NNP+의/JKG",
    "split_answer": [
      [
        "공감",
        "NNP"
      ],
      [
        "의",
        "JKG"
      ]
    ]
  }
]