[
  {
    "text": "식사도 그렇지만 교통비가 많이 들고 얘가 술을 좋아하니까",
    "answer": "그렇/VA+지만/EC",
    "split_answer": [
      [
        "그렇",
        "VA"
      ],
      [
        "지만",
        "EC"
      ]
    ]
  },
  {
    "text": "형식적으로는 그렇지만 지금 이 사안은 여러 번 말씀드린다만 어 기본적인 인간에 존엄성에 관한 문제이고 국가에 인권보장에 관한 문제이기 때문에 그런 일반 개인 민간 기업이 하는 그런 항소권은 이번 사안에 대해서는 외교부가 행사해서는 안 된다고 생각합니다.",
    "answer": "그렇/VA+지만/EC",
    "split_answer": [
      [
        "그렇",
        "VA"
      ],
      [
        "지만",
        "EC"
      ]
    ]
  },
  {
    "text": "그렇지만 표정관리 하시는 그 후보가 새누리당 안에 있는 겁니까",
    "answer": "그렇/VA+지만/EC",
    "split_answer": [
      [
        "그렇",
        "VA"
      ],
      [
        "지만",
        "EC"
      ]
    ]
  },
  {
    "text": "그렇지만 그 이 교육과학기술 정책은 현장에 변화가 핵심인데요.",
    "answer": "그렇지만/MAJ",
    "split_answer": [
      "그렇지만",
      "MAJ"
    ]
  },
  {
    "text": "그렇지만 지금은 그 조항이 유일한 동아줄이 되고 있다.",
    "answer": "그렇지만/MAJ",
    "split_answer": [
      "그렇지만",
      "MAJ"
    ]
  },
  {
    "text": "그렇지만 또 한편 다행인 것은 그 어려운 상황에서도 뭔가 새로운 희망을 찾고자 하는 농업인들이 많이 계시다는 것을 제가 느낀게 이겁니다.",
    "answer": "그렇지만/MAJ",
    "split_answer": [
      "그렇지만",
      "MAJ"
    ]
  }
]