[
  {
    "text": "그래 가지고 끝내는 사위 앞으로 안 오고 딸 앞으로 하더라 야",
    "answer": "끝내/MAG+는/JX",
    "split_answer": [
      [
        "끝내",
        "MAG"
      ],
      [
        "는",
        "JX"
      ]
    ]
  },
  {
    "text": "끝내는 지금 재심청구가 기각이 됐는데.",
    "answer": "끝내/MAG+는/JX",
    "split_answer": [
      [
        "끝내",
        "MAG"
      ],
      [
        "는",
        "JX"
      ]
    ]
  },
  {
    "text": "근데 나는 그 빨리 끝내는 게 일단 안 되니까.",
    "answer": "끝내/VV+는/ETM",
    "split_answer": [
      [
        "끝내",
        "VV"
      ],
      [
        "는",
        "ETM"
      ]
    ]
  },
  {
    "text": "무리한 욕심 대신 '3온'을 하더라도 '1퍼트'에 끝내는 전략적인 플레이는 시니어투어 선수들이 더 낫다는 이야기다.",
    "answer": "끝내/VV+는/ETM",
    "split_answer": [
      [
        "끝내",
        "VV"
      ],
      [
        "는",
        "ETM"
      ]
    ]
  }
]