[
  {
    "text": "이제 대개 환갑 여행이라든가 연령대가 좀 많이 높으니까 좀 재미없어 하더라.",
    "answer": "재미없/VA+어/EC",
    "split_answer": [
      [
        "재미없",
        "VA"
      ],
      [
        "어",
        "EC"
      ]
    ]
  },
  {
    "text": "그러다 보니까 애들이 재미없어 하고 두 번 다시 이제 안 간다 하고 엄마랑 안 간다 하고",
    "answer": "재미없/VA+어/EC",
    "split_answer": [
      [
        "재미없",
        "VA"
      ],
      [
        "어",
        "EC"
      ]
    ]
  },
  {
    "text": "드라마 안 봐 재미없어",
    "answer": "재미없/VA+어/EF",
    "split_answer": [
      [
        "재미없",
        "VA"
      ],
      [
        "어",
        "EF"
      ]
    ]
  },
  {
    "text": "근데 여긴 재미없어",
    "answer": "재미없/VA+어/EF",
    "split_answer": [
      [
        "재미없",
        "VA"
      ],
      [
        "어",
        "EF"
      ]
    ]
  }
]