[
  {
    "text": "할머니께서 직접 주기를 바랬나보다",
    "answer": "주/VV+기/ETN+를/JKO",
    "split_answer": [
      [
        "주",
        "VV"
      ],
      [
        "기",
        "ETN"
      ],
      [
        "를",
        "JKO"
      ]
    ]
  },
  {
    "text": "북한은 그거를 없애 주기를 굉장히 바랬어요.",
    "answer": "주/VX+기/ETN+를/JKO",
    "split_answer": [
      [
        "주",
        "VX"
      ],
      [
        "기",
        "ETN"
      ],
      [
        "를",
        "JKO"
      ]
    ]
  },
  {
    "text": "할부의 개념을 빌린 렌털 서비스도 제품 교체 주기를 반영했다.",
    "answer": "주기/NNG+를/JKO",
    "split_answer": [
      [
        "주기",
        "NNG"
      ],
      [
        "를",
        "JKO"
      ]
    ]
  }
]