[
  {
    "text": "고 분야 별로 경쟁을 하게 돼 있습니다.",
    "answer": "하/VV+게/EC",
    "split_answer": [
      [
        "하",
        "VV"
      ],
      [
        "게",
        "EC"
      ]
    ]
  },
  {
    "text": "그런 생각을 하게 됩니다",
    "answer": "하/VV+게/EC",
    "split_answer": [
      [
        "하",
        "VV"
      ],
      [
        "게",
        "EC"
      ]
    ]
  },
  {
    "text": "그런데 가셔서 무조건 귀농을 하게 되잖아요? 그러면 실패할 확률이 굉장히 많아요.",
    "answer": "하/VV+게/EC",
    "split_answer": [
      [
        "하",
        "VV"
      ],
      [
        "게",
        "EC"
      ]
    ]
  },
  {
    "text": "서울에서도 쇼핑 하게 하고",
    "answer": "하/XSV+게/EC",
    "split_answer": [
      [
        "하",
        "XSV"
      ],
      [
        "게",
        "EC"
      ]
    ]
  },
  {
    "text": "평생 사회의 귀하는 일이 아니겠냐 싶어서 한방 병원을 설립 하게 됐습니다",
    "answer": "하/XSV+게/EC",
    "split_answer": [
      [
        "하",
        "XSV"
      ],
      [
        "게",
        "EC"
      ]
    ]
  },
  {
    "text": "약간 꽁 하게 되는 그런 거 있잖아요.",
    "answer": "하/XSV+게/EC",
    "split_answer": [
      [
        "하",
        "XSV"
      ],
      [
        "게",
        "EC"
      ]
    ]
  }
]