[
  {
    "text": "하지만 특정 지역과 금력에 치우친 정당이어서 정통 보수정당이라고 하긴 어렵다.",
    "answer": "하/VV+기/ETN+ㄴ/JX",
    "split_answer": [
      [
        "하",
        "VV"
      ],
      [
        "기",
        "ETN"
      ],
      [
        "ㄴ",
        "JX"
      ]
    ]
  },
  {
    "text": "그쪽에서도 그다지 서로 물밑에서 대화를 하긴 했을 텐데",
    "answer": "하/VV+기/ETN+ㄴ/JX",
    "split_answer": [
      [
        "하",
        "VV"
      ],
      [
        "기",
        "ETN"
      ],
      [
        "ㄴ",
        "JX"
      ]
    ]
  },
  {
    "text": "피곤하게 하긴 해야 돼",
    "answer": "하/VX+기/ETN+ㄴ/JX",
    "split_answer": [
      [
        "하",
        "VX"
      ],
      [
        "기",
        "ETN"
      ],
      [
        "ㄴ",
        "JX"
      ]
    ]
  },
  {
    "text": "그냥 좋은 마음으로 하고 있는데 어쩔 땐 조금 힘들기도 하긴 해요.",
    "answer": "하/VX+기/ETN+ㄴ/JX",
    "split_answer": [
      [
        "하",
        "VX"
      ],
      [
        "기",
        "ETN"
      ],
      [
        "ㄴ",
        "JX"
      ]
    ]
  }
]