[
  {
    "text": "반응이 없어도 좋으니 음악을 다시 해야겠다고 결심했죠.”",
    "answer": "하/VV+아야/EC+하/VX+겠/EP+다고/EC",
    "split_answer": [
      [
        "하",
        "VV"
      ],
      [
        "아야",
        "EC"
      ],
      [
        "하",
        "VX"
      ],
      [
        "겠",
        "EP"
      ],
      [
        "다고",
        "EC"
      ]
    ]
  },
  {
    "text": "부족하지만 후배들을 위해 뭔가 해야겠다고 생각했죠.\"",
    "answer": "하/VV+아야/EC+하/VX+겠/EP+다고/EC",
    "split_answer": [
      [
        "하",
        "VV"
      ],
      [
        "아야",
        "EC"
      ],
      [
        "하",
        "VX"
      ],
      [
        "겠",
        "EP"
      ],
      [
        "다고",
        "EC"
      ]
    ]
  },
  {
    "text": "사람들이 걱정하니 밥을 먹기는 해야겠다.",
    "answer": "하/VX+아야/EC+하/VX+겠/EP+다고/EC",
    "split_answer": [
      [
        "하",
        "VX"
      ],
      [
        "아야",
        "EC"
      ],
      [
        "하",
        "VX"
      ],
      [
        "겠",
        "EP"
      ],
      [
        "다고",
        "EC"
      ]
    ]
  },
  {
    "text": "너무 늦었으니 애들을 자게 해야겠다.",
    "answer": "하/VX+아야/EC+하/VX+겠/EP+다고/EC",
    "split_answer": [
      [
        "하",
        "VX"
      ],
      [
        "아야",
        "EC"
      ],
      [
        "하",
        "VX"
      ],
      [
        "겠",
        "EP"
      ],
      [
        "다고",
        "EC"
      ]
    ]
  }
]