[
  {
    "text": "한편 중국 기업들의 한국 브랜드 인수는 패션업계부터 본격화됐다.",
    "answer": "한편/MAG",
    "split_answer": [
      "한편",
      "MAG"
    ]
  },
  {
    "text": "한편 CNN머니는 재난 평가 업체를 인용해 \"'어마'와 2주 전 텍사스를 강타한 허리케인 '하비'로 인한 경제적 피해가 최대 2620억달러(약 295조원)에 달할 전망\"이라고 보도했다.",
    "answer": "한편/MAG",
    "split_answer": [
      "한편",
      "MAG"
    ]
  },
  {
    "text": "한편 정부는 물가대책과 별도로 중소기업에 20조9000억 원의 자금을 신규 공급하기로 했다.",
    "answer": "한편/MAG",
    "split_answer": [
      "한편",
      "MAG"
    ]
  },
  {
    "text": "한편 4일 대전 경기에서는 삼성화재가 우리카드를 3-1(25-16, 25-20, 23-25, 25-23)로 꺾고 정규시즌 우승에 한발 더 다가갔다.",
    "answer": "한편/MAG",
    "split_answer": [
      "한편",
      "MAG"
    ]
  },
  {
    "text": "한편 위성 발사 실패의 책임을 물어 숙청 가능성이 제기됐던 담당자 3인방은 건재한 것으로 나타났다.",
    "answer": "한편/MAG",
    "split_answer": [
      "한편",
      "MAG"
    ]
  },
  {
    "text": "한편 사우디아라비아가 최근 시리아 반군에게 무기 지원을 시작한 것으로 알려졌는데, 이 역시 미국 등의 입장 변화와 관련이 있다는 해석이다.",
    "answer": "한편/MAG",
    "split_answer": [
      "한편",
      "MAG"
    ]
  },
  {
    "text": "한편 이날 신규 에이아이 의심신고는 1건(경기 안성)으로 진정 국면이 유지되고 있다.",
    "answer": "한편/MAG",
    "split_answer": [
      "한편",
      "MAG"
    ]
  },
  {
    "text": "한편 문재인 대표와의 ‘혁신 경쟁’을 예고한 안철수 의원은 23일 ‘인적 쇄신’과 관련한 혁신위원회 기자회견 직후 최재천 정책위의장과 함께 ‘공직자윤리법 개정’ 간담회를 열기로 했다.",
    "answer": "한편/MAG",
    "split_answer": [
      "한편",
      "MAG"
    ]
  },
  {
    "text": "한편 서울시는 설날인 28일과 29일 이틀간 지하철 운행을 평소보다 179회(20∼30분 간격) 늘린다고 밝혔다.",
    "answer": "한편/MAG",
    "split_answer": [
      "한편",
      "MAG"
    ]
  },
  {
    "text": "한편 올 시즌 프로농구 관중은 이날까지 100만2608명을 기록하며, 역대 최소 경기(234경기) 100만 관중을 넘어섰다.",
    "answer": "한편/MAG",
    "split_answer": [
      "한편",
      "MAG"
    ]
  },
  {
    "text": "한편 응시자들 사이에선 도식적 추리 영역이 어려웠다는 반응도 많았다.",
    "answer": "한편/MAG",
    "split_answer": [
      "한편",
      "MAG"
    ]
  },
  {
    "text": "한편 롯데면세점 월드타워점은 개장을 기념해 한류 스타인 배우 김수현을 전속모델로 내세워 활발한 홍보활동을 벌이고 있다.",
    "answer": "한편/MAG",
    "split_answer": [
      "한편",
      "MAG"
    ]
  },
  {
    "text": "정보전자소재 사업본부는 편광판 등 기존 분야에서 수익성을 강화하는 한편 유기발광다이오드(OLED) 패널 등 신사업 분야의 경쟁력도 강화하기로 했다.",
    "answer": "한편/NNG",
    "split_answer": [
      "한편",
      "NNG"
    ]
  },
  {
    "text": "퍼스트라운지는 미술관을 콘셉트로 유럽풍의 클래식한 분위기를 연출하는 한편 비즈니스라운지는 도서관 이미지를 살린 것이 특징.",
    "answer": "한편/NNG",
    "split_answer": [
      "한편",
      "NNG"
    ]
  },
  {
    "text": "국토교통부는 20일 정부서울청사에서 열린 ‘포항지진 관계장관회의’를 거쳐, 지진으로 파손된 주택에 대한 복구를 위한 융자지원금 480억원을 주택도시기금에서 긴급 편성하는 한편 지진 피해를 입지 않은 다른 지역 주택들의 내진보강을 지원하기 위한 융자금도 200억원을 편성하기로 했다고 밝혔다.",
    "answer": "한편/NNG",
    "split_answer": [
      "한편",
      "NNG"
    ]
  },
  {
    "text": "이들은 연고지인 고양시를 널리 알리는 한편 지역사회 공헌 활동에도 적극적으로 나서고 있다.",
    "answer": "한편/NNG",
    "split_answer": [
      "한편",
      "NNG"
    ]
  },
  {
    "text": "치솟은 배추 가격 안정을 위해 정부가 배추 수입 시 적용하는 관세를 한시적으로 폐지하는 한편 중국산 배추를 추가 수입하는 방안을 검토하기로 했다.",
    "answer": "한편/NNG",
    "split_answer": [
      "한편",
      "NNG"
    ]
  },
  {
    "text": "그러나 스페인 공공노조는 임금 삭감에 항의, 일요일인 16일 마드리드 도심에서 대규모 시위를 벌이는 한편 오는 6월 2일 전국단위 총파업을 예고하며 강력 반발하고 있다.",
    "answer": "한편/NNG",
    "split_answer": [
      "한편",
      "NNG"
    ]
  },
  {
    "text": "백화점들은 이 같은 상황을 돌파하기 위해 온라인몰과 모바일 앱을 강화하는 한편 신규 사업 투자를 늘리는 정공법을 택하고 있다.",
    "answer": "한편/NNG",
    "split_answer": [
      "한편",
      "NNG"
    ]
  },
  {
    "text": "업계의 블랙리스트에 올라 다른 취직길도 막힌 그는 값나가는 개들을 산책시키는 한편 역할대행업체의 아르바이트와 식당 불판 닦이로 근근이 생계를 해결한다.",
    "answer": "한편/NNG",
    "split_answer": [
      "한편",
      "NNG"
    ]
  },
  {
    "text": "청와대는 20일 국가안전보장회의(NSC) 산하에 상설 상임위원회와 사무처를 설치하는 한편 국가안보실의 기능·조직을 확충하는 내용의 'NSC 활성화 및 국가안보실 강화안'을 발표했다.",
    "answer": "한편/NNG",
    "split_answer": [
      "한편",
      "NNG"
    ]
  },
  {
    "text": "콜베르 위원회는 여름철 해외여행을 떠나는 관광객에게 “모조품을 구입하지 말자”고 부탁하는 한편 국내에서도 모조품을 발견할 경우 즉각 신고해줄 것을 요청했다.",
    "answer": "한편/NNG",
    "split_answer": [
      "한편",
      "NNG"
    ]
  },
  {
    "text": "또 폐기물 에너지화 추진을 위해 매립·소각시설 설치에 대한 국고 지원을 점차 줄이고 매립 부과금을 물리는 한편 에너지화시설 조성을 위해 관련 규제도 완화한다.",
    "answer": "한편/NNG",
    "split_answer": [
      "한편",
      "NNG"
    ]
  },
  {
    "text": "요즘은 국내외 거래처와의 인맥 쌓기에 주력하는 한편 러시아 기업 2곳을 대상으로 마케팅 활동을 하고 있다.",
    "answer": "한편/NNG",
    "split_answer": [
      "한편",
      "NNG"
    ]
  }
]