[
  {
    "text": "뭐 연세 드신 분들도 좋아하지만 애들도 굉장히 좋아하죠.",
    "answer": "연세/NNG",
    "split_answer": [
      "연세",
      "NNG"
    ]
  },
  {
    "text": "아버진 연세 드셔서 성당에 나갔어요.",
    "answer": "연세/NNG",
    "split_answer": [
      "연세",
      "NNG"
    ]
  },
  {
    "text": "근데 연세 있으시니까 잘 삐지시더라",
    "answer": "연세/NNG",
    "split_answer": [
      "연세",
      "NNG"
    ]
  },
  {
    "text": "연세 있으신 분들은 아 저거 혹시 과격 시위",
    "answer": "연세/NNG",
    "split_answer": [
      "연세",
      "NNG"
    ]
  },
  {
    "text": "이렇게 보면은 연세 항외과 있어.",
    "answer": "연세/NNP",
    "split_answer": [
      "연세",
      "NNP"
    ]
  },
  {
    "text": "다른 긍까 표준국어대사전만이 아니라 실제로 께 면세 연세 한국어사전이나",
    "answer": "연세/NNP",
    "split_answer": [
      "연세",
      "NNP"
    ]
  },
  {
    "text": "근데 여기서의 저도 한글이 뭔가라고 해 갖고 우리 한글 연세 한국어 사전 찾아봤어요.",
    "answer": "연세/NNP",
    "split_answer": [
      "연세",
      "NNP"
    ]
  },
  {
    "text": "그래서 우리 그 그 연세 한국어 사전이 나왔을 때 너무나도 제가 기뻤답니다.",
    "answer": "연세/NNP",
    "split_answer": [
      "연세",
      "NNP"
    ]
  }
]