[
  {
    "text": "그러나 경희대 범죄심리학과 이수정 교수는 “일반적 재소자와 비교할 때 22점도 낮은 점수가 아니다”라며 전봇대 뒤에 숨어 있었다거나, 시신을 잔혹하게 훼손하고 유기를 위해 검은 봉투를 산 행위도 오가 나름대로는 머리를 쓴 것이라고 말했다.",
    "answer": "오/NNP+가/JKS",
    "split_answer": [
      [
        "오",
        "NNP"
      ],
      [
        "가",
        "JKS"
      ]
    ]
  },
  {
    "text": "자 저 다 오가 이렇게 됐네요. 이렇게 다.",
    "answer": "오/NR+가/JKS",
    "split_answer": [
      [
        "오",
        "NR"
      ],
      [
        "가",
        "JKS"
      ]
    ]
  },
  {
    "text": "오가 유코(28), 요시다 아사미(23) 등 작고 빠른 가드진을 앞세운 일본을 상대하기 위해서도 가드진 보강은 필요했다.",
    "answer": "오가/NNP",
    "split_answer": [
      "오가",
      "NNP"
    ]
  }
]