[
  {
    "text": "그래서 요게 찬물에 얼음 넣고 아주 잘 우려 저 저",
    "answer": "우리/VV+어/EC",
    "split_answer": [
      [
        "우리",
        "VV"
      ],
      [
        "어",
        "EC"
      ]
    ]
  },
  {
    "text": "맛있게 우려 낸 국물로 사용하고요.",
    "answer": "우리/VV+어/EC",
    "split_answer": [
      [
        "우리",
        "VV"
      ],
      [
        "어",
        "EC"
      ]
    ]
  },
  {
    "text": "어머니는 멸치를 우려 국물을 만드셨다.",
    "answer": "우리/VV+어/EC",
    "split_answer": [
      [
        "우리",
        "VV"
      ],
      [
        "어",
        "EC"
      ]
    ]
  },
  {
    "text": "녹차는 끓는 물보다 약간 식은 물에 우려 마시는 것이 좋다.",
    "answer": "우리/VV+어/EC",
    "split_answer": [
      [
        "우리",
        "VV"
      ],
      [
        "어",
        "EC"
      ]
    ]
  }
]