[
  {
    "text": "이런 ‘트렌드’의 원조가 바로 두산이다.",
    "answer": "원조/NNG+가/JKS",
    "split_answer": [
      [
        "원조",
        "NNG"
      ],
      [
        "가",
        "JKS"
      ]
    ]
  },
  {
    "text": "유니세프는 위기 상황을 완화하기 위해서는 앞으로 3개월 동안에만 3190만 달러의 원조가 필요하다며 국제사회의 긴급 지원을 요청했다.",
    "answer": "원조/NNG+가/JKS",
    "split_answer": [
      [
        "원조",
        "NNG"
      ],
      [
        "가",
        "JKS"
      ]
    ]
  },
  {
    "text": "이런 원조가 될 수 있도록 우리가 기여할 예정입니다",
    "answer": "원조/NNG+가/JKC",
    "split_answer": [
      [
        "원조",
        "NNG"
      ],
      [
        "가",
        "JKC"
      ]
    ]
  },
  {
    "text": "이거는 전통적인 원조가 아니다.",
    "answer": "원조/NNG+가/JKC",
    "split_answer": [
      [
        "원조",
        "NNG"
      ],
      [
        "가",
        "JKC"
      ]
    ]
  }
]