[
  {
    "text": "전경련 요구를 100% 수용한 것은 아니지만 점수와 순위를 공개하지 않고, 전체 평가 대상의 87.5%에 ‘보통’ 이상의 등급을 부여함으로써 사실상 재계의 요구를 들어준 셈이 됐다.",
    "answer": "이상/NNG+의/JKG",
    "split_answer": [
      [
        "이상",
        "NNG"
      ],
      [
        "의",
        "JKG"
      ]
    ]
  },
  {
    "text": "결의안 채택은 회원국 3분의 2 이상의 찬성이 있어야 하고, 상임이사국 5곳 가운데 한 나라라도 반대를 하지 않아야 한다.",
    "answer": "이상/NNG+의/JKG",
    "split_answer": [
      [
        "이상",
        "NNG"
      ],
      [
        "의",
        "JKG"
      ]
    ]
  },
  {
    "text": "이상의 ‘날개’나 ‘권태’의 책장을 마주하듯, 무표정하되 복잡한 수식구의 한글로 독창적 랩 풍경을 그리는 게 그의 장기다.",
    "answer": "이상/NNP+의/JKG",
    "split_answer": [
      [
        "이상",
        "NNP"
      ],
      [
        "의",
        "JKG"
      ]
    ]
  },
  {
    "text": "김유정의 '동백꽃', 이상의 '날개', 이효석의 '메밀꽃 필 무렵', 김동리의 '무녀도', 황순원의 '목넘이 마을의 개', 김승옥의 '무진기행', 최인호의 '타인의 방', 황석영의 '삼포 가는 길', 김주영의 '도둑견습', 오정희의 '중국인 거리', 서영은의 '먼 그대', 임철우의 '사평역', 이창동의 '소지', 양귀자의 '원미동 시인' 등이 배우들의 음성으로 전달된다.",
    "answer": "이상/NNP+의/JKG",
    "split_answer": [
      [
        "이상",
        "NNP"
      ],
      [
        "의",
        "JKG"
      ]
    ]
  }
]