[
  {
    "text": "이번에 승부를 펼치는 이세돌과 알파고의 경우에도, 33살의 이 9단은 지금까지 1만번의 대국을 치렀지만, 2살에 불과한 알파고는 10만번의 경기를 연습했다.",
    "answer": "이세돌/NNP+과/JC",
    "split_answer": [
      [
        "이세돌",
        "NNP"
      ],
      [
        "과",
        "JC"
      ]
    ]
  },
  {
    "text": "지난해 이세돌과 겨루기 전의 알파고 스파링 상대였던 판후이는 황인성과 프랑스 바둑협회서 잠시 함께 몸담았을 때 \"우리 둘이 노조를 만들자\"며 농담을 건네올 정도로 막역한 사이다.",
    "answer": "이세돌/NNP+과/JKB",
    "split_answer": [
      [
        "이세돌",
        "NNP"
      ],
      [
        "과",
        "JKB"
      ]
    ]
  }
]