[
  {
    "text": "부산 덕포동 여중생 이모(13)양 성폭행 살해 피의자 김길태(33)는 이양을 납치해 인근 빈집으로 끌고가 성폭행하는 과정에서 바로 살해한 후 시신 옆에서 잠을 잔 것으로 드러났다.",
    "answer": "이/NNP+양/NNB+을/JKO",
    "split_answer": [
      [
        "이",
        "NNP"
      ],
      [
        "양",
        "NNB"
      ],
      [
        "을",
        "JKO"
      ]
    ]
  },
  {
    "text": "그는 \"이런 위협이 계속된다면 오는 2012년으로 예정된 전시작전권 이양을 연기해야 한다\"고 밝혔다.",
    "answer": "이양/NNG+을/JKO",
    "split_answer": [
      [
        "이양",
        "NNG"
      ],
      [
        "을",
        "JKO"
      ]
    ]
  }
]