[
  {
    "text": "그래서 십이 일만 쉬었다가 온다고 했다.",
    "answer": "일/NNB+만/JX",
    "split_answer": [
      [
        "일",
        "NNB"
      ],
      [
        "만",
        "JX"
      ]
    ]
  },
  {
    "text": "원래 수렵 채집 할 때는 한 일주일에 한 이삼 일만 일하고",
    "answer": "일/NNB+만/JX",
    "split_answer": [
      [
        "일",
        "NNB"
      ],
      [
        "만",
        "JX"
      ]
    ]
  },
  {
    "text": "이제 메이저리그급의 시설을 갖췄으니 야구도 메이저리그처럼 잘하는 일만 남았습니다.",
    "answer": "일/NNG+만/JX",
    "split_answer": [
      [
        "일",
        "NNG"
      ],
      [
        "만",
        "JX"
      ]
    ]
  },
  {
    "text": "전자책출판 공동체를 내세운 일종의 협동조합이지만, 그 일만 할 리가 없다.",
    "answer": "일/NNG+만/JX",
    "split_answer": [
      [
        "일",
        "NNG"
      ],
      [
        "만",
        "JX"
      ]
    ]
  },
  {
    "text": "이 분의 일만 썰면 일 센치가 나오네요.",
    "answer": "일/NR+만/JX",
    "split_answer": [
      [
        "일",
        "NR"
      ],
      [
        "만",
        "JX"
      ]
    ]
  },
  {
    "text": "재적 인원의 삼 분의 일만 모여도 회의를 시작하는 걸로 하죠.",
    "answer": "일/NR+만/JX",
    "split_answer": [
      [
        "일",
        "NR"
      ],
      [
        "만",
        "JX"
      ]
    ]
  },
  {
    "text": "빈도가 그 일만 이상인 어절들만 대상으로 해서 작업을 하겠다.",
    "answer": "일만/NR",
    "split_answer": [
      "일만",
      "NR"
    ]
  },
  {
    "text": "지금 여군이 일만 명 시댄데",
    "answer": "일만/NR",
    "split_answer": [
      "일만",
      "NR"
    ]
  }
]