[
  {
    "text": "이처럼 중국인 관광객이 급증한 것은 무사증 입국과 국제직항노선 활성화를 위한 인센티브 정책이 주효했던 것으로 제주도는 분석했다.",
    "answer": "입국/NNG+과/JC",
    "split_answer": [
      [
        "입국",
        "NNG"
      ],
      [
        "과",
        "JC"
      ]
    ]
  },
  {
    "text": "이들은 주로 러시아, 우즈베키스탄, 카자흐스탄, 모로코, 콜롬비아, 몽골, 중국, 필리핀, 태국, 캄보디아 출신인데 이들의 입국을 주선한 브로커들이 한국의 고용주나 남편에게서 2만달러까지 돈을 받아 외국인 노동자나 신부는 한국 입국과 동시에 빚더미에 앉는다는 것이다.",
    "answer": "입국/NNG+과/JKB",
    "split_answer": [
      [
        "입국",
        "NNG"
      ],
      [
        "과",
        "JKB"
      ]
    ]
  }
]