[
  {
    "text": "정씨는 \"인왕산을 찾는 등산객과 수많은 주민이 내가 그린 그림을 본다고 생각하니 설렌다\"고 말했다.",
    "answer": "보/VV+ㄴ다고/EC",
    "split_answer": [
      [
        "보",
        "VV"
      ],
      [
        "ㄴ다고",
        "EC"
      ]
    ]
  },
  {
    "text": "반면 윤 의원 측은 정상회담 뒤에 열린 남북 국방장관 회담을 위해 우리 측에서 준비한 지도에도 합참 통제선이 표시돼 있었던 만큼 기밀 보호에 대한 충분하고 적절한 조치가 이뤄졌을 것으로 본다고 반박하고 있다.",
    "answer": "보/VV+ㄴ다고/EC",
    "split_answer": [
      [
        "보",
        "VV"
      ],
      [
        "ㄴ다고",
        "EC"
      ]
    ]
  },
  {
    "text": "지금 쫌 그래도 생각해 본다고 막 하던데?",
    "answer": "보/VX+ㄴ다고/EC",
    "split_answer": [
      [
        "보",
        "VX"
      ],
      [
        "ㄴ다고",
        "EC"
      ]
    ]
  },
  {
    "text": "뭘 생각해 본다고 했는데",
    "answer": "보/VX+ㄴ다고/EC",
    "split_answer": [
      [
        "보",
        "VX"
      ],
      [
        "ㄴ다고",
        "EC"
      ]
    ]
  }
]