[
  {
    "text": "그런 의미에서 본다 그런다면은",
    "answer": "보/VV+ㄴ다/EF",
    "split_answer": [
      [
        "보",
        "VV"
      ],
      [
        "ㄴ다",
        "EF"
      ]
    ]
  },
  {
    "text": "뭐 이런 대목에서 본다 그런다면은",
    "answer": "보/VV+ㄴ다/EF",
    "split_answer": [
      [
        "보",
        "VV"
      ],
      [
        "ㄴ다",
        "EF"
      ]
    ]
  },
  {
    "text": "재개발 상세정보 인터넷서 본다",
    "answer": "보/VV+ㄴ다/EF",
    "split_answer": [
      [
        "보",
        "VV"
      ],
      [
        "ㄴ다",
        "EF"
      ]
    ]
  },
  {
    "text": "그 다음에 내부적인 어떤 통합의를 생각해 본다",
    "answer": "보/VX+ㄴ다/EF",
    "split_answer": [
      [
        "보",
        "VX"
      ],
      [
        "ㄴ다",
        "EF"
      ]
    ]
  },
  {
    "text": "괜히 혹시 전화 오는 거 아닌가 막 이런 이런 생각은 가끔씩 해 본다 그랬더니",
    "answer": "보/VX+ㄴ다/EF",
    "split_answer": [
      [
        "보",
        "VX"
      ],
      [
        "ㄴ다",
        "EF"
      ]
    ]
  },
  {
    "text": "뭔가 함께 한식 밥상을 만들어 본다 그랬는데",
    "answer": "보/VX+ㄴ다/EF",
    "split_answer": [
      [
        "보",
        "VX"
      ],
      [
        "ㄴ다",
        "EF"
      ]
    ]
  }
]