[
  {
    "text": "일각에선 대학의 자율성 보장이 사학법인이나 총장의 권한확대로 해석될 여지가 있기 때문에 대학의 사회적 책무성도 헌법에 명시해야 한단 주장도 나옵니다.",
    "answer": "보장/NNG+이/JKS",
    "split_answer": [
      [
        "보장",
        "NNG"
      ],
      [
        "이",
        "JKS"
      ]
    ]
  },
  {
    "text": "그런 걸 찾았다손 치드래도 그쪽에서 자기를 받아준다는 보장이 없는 것이죠",
    "answer": "보장/NNG+이/JKS",
    "split_answer": [
      [
        "보장",
        "NNG"
      ],
      [
        "이",
        "JKS"
      ]
    ]
  },
  {
    "text": "그렇지만 그것이 꼭 그렇게 되리 되리라는 보장이 있다는 것은",
    "answer": "보장/NNG+이/JKS",
    "split_answer": [
      [
        "보장",
        "NNG"
      ],
      [
        "이",
        "JKS"
      ]
    ]
  },
  {
    "text": "큰 당이든 작은 당이든 모든 후보에게 공정한 기회가 보장이 돼야 된다고 봐요.",
    "answer": "보장/NNG+이/JKS",
    "split_answer": [
      [
        "보장",
        "NNG"
      ],
      [
        "이",
        "JKS"
      ]
    ]
  },
  {
    "text": "때문에 창당이란 것은 미래가 보장이 되어야 하는 거거든요.",
    "answer": "보장/NNG+이/JKC",
    "split_answer": [
      [
        "보장",
        "NNG"
      ],
      [
        "이",
        "JKC"
      ]
    ]
  },
  {
    "text": "어 보장이 안되는 거 같고",
    "answer": "보장/NNG+이/JKC",
    "split_answer": [
      [
        "보장",
        "NNG"
      ],
      [
        "이",
        "JKC"
      ]
    ]
  },
  {
    "text": "근데 휴일이 보장이 되니까 너무 좋아",
    "answer": "보장/NNG+이/JKC",
    "split_answer": [
      [
        "보장",
        "NNG"
      ],
      [
        "이",
        "JKC"
      ]
    ]
  },
  {
    "text": "그는 “(미국이) 대만에 무기를 판매한다고 (유사시) 대만의 안전이 보장되는가. 중국 주변에서 무력 충돌이 발생하면 (사드는커녕) 미국의 항공모함인들 충분한 보장이 될 것인가”라고 되물었다.",
    "answer": "보장/NNG+이/JKC",
    "split_answer": [
      [
        "보장",
        "NNG"
      ],
      [
        "이",
        "JKC"
      ]
    ]
  }
]