[
  {
    "text": "비문 단일 후보를 뽑자 이런 움직임이 또 있겠죠.",
    "answer": "비/XPN+문/NNP",
    "split_answer": [
      [
        "비",
        "XPN"
      ],
      [
        "문",
        "NNP"
      ]
    ]
  },
  {
    "text": "그러면은 비박 비문",
    "answer": "비/XPN+문/NNP",
    "split_answer": [
      [
        "비",
        "XPN"
      ],
      [
        "문",
        "NNP"
      ]
    ]
  },
  {
    "text": "오히려 적절한 시기에 연꽃 문양 대리석을 걷어내고 비문 공개를 추진할 계획”이라며 이들의 제안을 거절했다고 한다.",
    "answer": "비문/NNG",
    "split_answer": [
      "비문",
      "NNG"
    ]
  },
  {
    "text": "설립 직후 이런 사실을 알게 된 이 단체는 비문 삭제를 요구했다.",
    "answer": "비문/NNG",
    "split_answer": [
      "비문",
      "NNG"
    ]
  }
]