[
  {
    "text": "15일 이 씨는 초록우산 어린이재단으로부터 전화 한 통을 받았다.",
    "answer": "통/NNB+을/JKO",
    "split_answer": [
      [
        "통",
        "NNB"
      ],
      [
        "을",
        "JKO"
      ]
    ]
  },
  {
    "text": "그 직원은 곧 문자 한 통을 보내왔습니다.",
    "answer": "통/NNB+을/JKO",
    "split_answer": [
      [
        "통",
        "NNB"
      ],
      [
        "을",
        "JKO"
      ]
    ]
  },
  {
    "text": "“우리가 개울로 놀러 가지만 않았어도, 놀러 가서 고기잡이를 하지 말고 미역만 감고 왔어도, 우유 끓이고 전지분유 담은 통을 부엌에 두지만 않았어도”라는 죄책감과 후회로 눈물이 쏟아졌다.",
    "answer": "통/NNG+을/JKO",
    "split_answer": [
      [
        "통",
        "NNG"
      ],
      [
        "을",
        "JKO"
      ]
    ]
  },
  {
    "text": "하지만 메블루트가 보자 통을 들고 거리를 나서며 혼자 뇌까리는 말은 독자의 허를 찌른다.",
    "answer": "통/NNG+을/JKO",
    "split_answer": [
      [
        "통",
        "NNG"
      ],
      [
        "을",
        "JKO"
      ]
    ]
  }
]