[
  {
    "text": "이날 공개된 노동당 규약 서문 개정판은 ‘조선노동당은 위대한 김일성 동지와 김정일 동지의 당이며 김일성-김정일주의를 유일한 지도사상으로 한다’고 규정했다.",
    "answer": "동지/NNG+와/JC",
    "split_answer": [
      [
        "동지",
        "NNG"
      ],
      [
        "와",
        "JC"
      ]
    ]
  },
  {
    "text": "<조선중앙텔레비전>과 <평양방송> 등 북한 매체들은 이날 8시뉴스에서 김 제1비서 소식을 보도하면서 “김정은 원수를 모시고 능라인민유원지 준공식이 성대히 진행됐다”며 “환영곡이 울리는 가운데 김정은 원수가 부인 리설주 동지와 함께 준공식장에 나왔다”고 보도했다.",
    "answer": "동지/NNG+와/JKB",
    "split_answer": [
      [
        "동지",
        "NNG"
      ],
      [
        "와",
        "JKB"
      ]
    ]
  }
]