[
  {
    "text": "근데 그 얘기를 오늘 처음 들어서 많이 놀랐다",
    "answer": "듣/VV+어서/EC",
    "split_answer": [
      [
        "듣",
        "VV"
      ],
      [
        "어서",
        "EC"
      ]
    ]
  },
  {
    "text": "이런 학생들 나중에 훨씬 성장할 가능성이 높다라는 걸 들어서 걱정 안해",
    "answer": "듣/VV+어서/EC",
    "split_answer": [
      [
        "듣",
        "VV"
      ],
      [
        "어서",
        "EC"
      ]
    ]
  },
  {
    "text": "콩쿠르 한 달 뒤엔 일본에서 리사이틀을 했는데 오신다는 소식을 들어서 너무 긴장했던 기억이 난다.",
    "answer": "듣/VV+어서/EC",
    "split_answer": [
      [
        "듣",
        "VV"
      ],
      [
        "어서",
        "EC"
      ]
    ]
  },
  {
    "text": "이렇게 제품의 소리를 들어서 나온 제품 중 하나가 마우스 워시(구강 청결제)입니다.\"",
    "answer": "듣/VV+어서/EC",
    "split_answer": [
      [
        "듣",
        "VV"
      ],
      [
        "어서",
        "EC"
      ]
    ]
  },
  {
    "text": "근까 잘 들어서 저 사람에게 맞는 반응을 해 줘야죠",
    "answer": "듣/VV+어서/EC",
    "split_answer": [
      [
        "듣",
        "VV"
      ],
      [
        "어서",
        "EC"
      ]
    ]
  },
  {
    "text": "저쪽에서 얘기하면 잘 들어서 조금 그냥 길 그렇게 길게 생각할 필요 없어요",
    "answer": "듣/VV+어서/EC",
    "split_answer": [
      [
        "듣",
        "VV"
      ],
      [
        "어서",
        "EC"
      ]
    ]
  }
]