[
  {
    "text": "인제 보험을 계속 이제 이렇게 좀 들었어요",
    "answer": "들/VV+었/EP+어요/EF",
    "split_answer": [
      [
        "들",
        "VV"
      ],
      [
        "었",
        "EP"
      ],
      [
        "어요",
        "EF"
      ]
    ]
  },
  {
    "text": "나? 몰 몰라요 어쨌든 반에서도 어쨌든 십 등 안엔 항상 들었어요",
    "answer": "들/VV+었/EP+어요/EF",
    "split_answer": [
      [
        "들",
        "VV"
      ],
      [
        "었",
        "EP"
      ],
      [
        "어요",
        "EF"
      ]
    ]
  },
  {
    "text": "이런 생각이 들었어요 저는.",
    "answer": "들/VV+었/EP+어요/EF",
    "split_answer": [
      [
        "들",
        "VV"
      ],
      [
        "었",
        "EP"
      ],
      [
        "어요",
        "EF"
      ]
    ]
  },
  {
    "text": "결혼 생활을 하면서도 그냥 미운 정 고운 정 다 들었어요",
    "answer": "들/VV+었/EP+어요/EF",
    "split_answer": [
      [
        "들",
        "VV"
      ],
      [
        "었",
        "EP"
      ],
      [
        "어요",
        "EF"
      ]
    ]
  }
]