[
  {
    "text": "이 후보자 동생이 이 후보자가 충남지사로 있던 2008년 천안시 아파트 시행사업과 관련해 변호사법 위반 혐의로 2011년 구속된 사건에 대해, 이 후보자는 “공소장에 ‘도지사인 이완구의 반대에도 불구하고’라고 명시돼 있다”며 무관함을 주장했다.",
    "answer": "사건/NNG+에/JKB",
    "split_answer": [
      [
        "사건",
        "NNG"
      ],
      [
        "에",
        "JKB"
      ]
    ]
  },
  {
    "text": "이번 어금니아빠 사건에 경우에는 이 위원회 소집 여부는 일단 지방청에 자체적인 판단에 따라 달려 있거든요.",
    "answer": "사건/NNG+에/JKG",
    "split_answer": [
      [
        "사건",
        "NNG"
      ],
      [
        "에",
        "JKG"
      ]
    ]
  }
]