[
  {
    "text": "안쪽에는 이렇게 다리 살만 있는 거",
    "answer": "살/NNG+만/JX",
    "split_answer": [
      [
        "살",
        "NNG"
      ],
      [
        "만",
        "JX"
      ]
    ]
  },
  {
    "text": "음 내가 우리 딸한테 야 너는 얼굴도 예쁜데 살만 좀 빼서",
    "answer": "살/NNG+만/JX",
    "split_answer": [
      [
        "살",
        "NNG"
      ],
      [
        "만",
        "JX"
      ]
    ]
  },
  {
    "text": "25일 AP통신과 홍콩 사우스차이나모닝포스트 등에 따르면 살만 쿠르시드 인도 외교장관은 “(중국과의 분쟁지역인) 아루나찰프라데시와 히말라야 일대의 아커싸이친이 중국 영토로 들어간 여권을 받아들일 수 없다”고 24일 비난했다.",
    "answer": "살만/NNP",
    "split_answer": [
      "살만",
      "NNP"
    ]
  },
  {
    "text": "이는 왕위 계승을 앞둔 모하메드 빈 살만 왕세자의 국가 온건화 개혁 비전 이공삼공에 따른 것으로",
    "answer": "살만/NNP",
    "split_answer": [
      "살만",
      "NNP"
    ]
  }
]