[
  {
    "text": "한화그룹은 연간 2.3GW의 셀 생산능력을 갖추게 됐다.",
    "answer": "셀/NNG",
    "split_answer": [
      "셀",
      "NNG"
    ]
  },
  {
    "text": "또 육각형의 셀 조각들이 수막현상을 감소시키는 ‘하이드로그립 솔’을 적용해 눈이나 얼음 위에서도 미끄럼방지 효과가 뛰어나다.",
    "answer": "셀/NNG",
    "split_answer": [
      "셀",
      "NNG"
    ]
  },
  {
    "text": "셀 간 거리를 지켜야 한다.",
    "answer": "셀/NNG",
    "split_answer": [
      "셀",
      "NNG"
    ]
  },
  {
    "text": "최대 셀 생산량을 확보해야 한다.",
    "answer": "셀/NNG",
    "split_answer": [
      "셀",
      "NNG"
    ]
  }
]