[
  {
    "text": "1986년 쿠바에서 녹음한 앨범이 15년 뒤 부부의 동의도 없이 발매되면서 바카 장관은 미국리코딩예술과학아카데미(NARAS)가 주최하는 2001년 라틴그래미어워드에서 수상하게 된다.",
    "answer": "수상/NNG+하/XSV+게/EC",
    "split_answer": [
      [
        "수상",
        "NNG"
      ],
      [
        "하",
        "XSV"
      ],
      [
        "게",
        "EC"
      ]
    ]
  },
  {
    "text": "하지만 이를 수상하게 여긴 울산시 감사팀이 경찰에 수사를 의뢰하면서 김씨의 범행을 밝혀냈다.",
    "answer": "수상하/VA+게/EC",
    "split_answer": [
      [
        "수상하",
        "VA"
      ],
      [
        "게",
        "EC"
      ]
    ]
  }
]